payload_wtf/__init__.py
payload_wtf/pwtf.py
payload_wtf-0.0.1.dist-info/METADATA
payload_wtf-0.0.1.dist-info/RECORD
payload_wtf-0.0.1.dist-info/WHEEL
payload_wtf-0.0.1.dist-info/top_level.txt
