Metadata-Version: 2.1
Name: payload-wtf
Version: 0.0.1
Summary: simple payload with an easy format for building Python APIs (like Django).
Home-page: https://github.com/yanwarsolah/payload-wtf
Author: Yanwar Solahudin
Author-email: yanwarsolah@gmail.com
License: UNKNOWN
Platform: UNKNOWN
Classifier: Programming Language :: Python :: 3
Classifier: License :: OSI Approved :: MIT License
Classifier: Operating System :: OS Independent
